LICENSE
beryl_events_utils/__init__.py
beryl_events_utils/main.py
beryl_events_utils-2.0.1.dist-info/LICENSE
beryl_events_utils-2.0.1.dist-info/WHEEL
beryl_events_utils-2.0.1.dist-info/METADATA
beryl_events_utils-2.0.1.dist-info/RECORD
